{
    "audit_opinions": {
        "values": [
            {
                "date": 2015,
                "rating": "unqualified",
                "report_url": "http://mfma.treasury.gov.za/Documents/07.%20Audit%20Reports/2014-15/03.%20District%20municipalities/DC8%20ZF%20Mgcawu/DC8%20Z%20F%20Mgcawu%20Audit%20report%202014-15.pdf",
                "result": "Unqualified - No findings"
            },
            {
                "date": 2014,
                "rating": "unqualified",
                "report_url": "http://mfma.treasury.gov.za/Documents/07.%20Audit%20Reports/2013-14/03.%20District%20municipalities/DC8%20ZF%20Mgcawu/DC8%20ZF%20Mgcawu%20Audit%20report%202013-14.pdf",
                "result": "Unqualified - No findings"
            },
            {
                "date": 2013,
                "rating": "unqualified",
                "report_url": null,
                "result": "Unqualified - No findings"
            },
            {
                "date": 2012,
                "rating": "unqualified_emphasis_of_matter",
                "report_url": "http://mfma.treasury.gov.za/Documents/07.%20Audit%20Reports/2011-12/03.%20District%20municipalities/DC8%20Siyanda/DC8%20Siyanda%20Audit%20report%202011-12.pdf",
                "result": "Unqualified - Emphasis of Matter items"
            }
        ]
    },
    "demarcation": {},
    "indicators": {
        "cap_budget_diff": {
            "ref": {
                "title": "Over and under spending reports to parliament",
                "url": "http://mfma.treasury.gov.za/Media_Releases/Reports%20to%20Parliament/Pages/default.aspx"
            },
            "values": [
                {
                    "date": 2015,
                    "overunder": "under",
                    "rating": "bad",
                    "result": -35.17
                },
                {
                    "date": 2014,
                    "overunder": "under",
                    "rating": "ave",
                    "result": -11.53
                },
                {
                    "date": 2013,
                    "overunder": "under",
                    "rating": "bad",
                    "result": -44.39
                },
                {
                    "date": 2012,
                    "overunder": "over",
                    "rating": "bad",
                    "result": 68687.01
                }
            ]
        },
        "cash_at_year_end": {
            "ref": {
                "title": "State of Local Government Finances",
                "url": "http://mfma.treasury.gov.za/Media_Releases/The%20state%20of%20local%20government%20finances/Pages/default.aspx"
            },
            "values": [
                {
                    "date": 2015,
                    "rating": "good",
                    "result": 104995.0
                },
                {
                    "date": 2014,
                    "rating": "good",
                    "result": 3307352.0
                },
                {
                    "date": 2013,
                    "rating": "good",
                    "result": 4923756.0
                },
                {
                    "date": 2012,
                    "rating": "good",
                    "result": 2543350.0
                }
            ]
        },
        "cash_coverage": {
            "ref": {
                "title": "State of Local Government Finances",
                "url": "http://mfma.treasury.gov.za/Media_Releases/The%20state%20of%20local%20government%20finances/Pages/default.aspx"
            },
            "values": [
                {
                    "date": 2015,
                    "rating": "bad",
                    "result": 0.0
                },
                {
                    "date": 2014,
                    "rating": "bad",
                    "result": 0.6
                },
                {
                    "date": 2013,
                    "rating": "bad",
                    "result": 1.0
                },
                {
                    "date": 2012,
                    "rating": "bad",
                    "result": 0.3
                }
            ]
        },
        "current_debtors_collection_rate": {
            "ref": {
                "title": "Municipal Budget and Reporting Regulations",
                "url": "http://mfma.treasury.gov.za/RegulationsandGazettes/Municipal%20Budget%20and%20Reporting%20Regulations/Pages/default.aspx"
            },
            "values": [
                {
                    "amount_type": "ACT",
                    "billing": [
                        0.0,
                        0.0,
                        0.0
                    ],
                    "date": "2017q1",
                    "month": 3,
                    "quarter": 1,
                    "rating": "bad",
                    "receipts": [
                        0.0,
                        0.0,
                        0.0
                    ],
                    "result": 0,
                    "year": 2017
                },
                {
                    "amount_type": "ACT",
                    "billing": [
                        0.0,
                        -886624.0,
                        0.0
                    ],
                    "date": "2016q4",
                    "month": 12,
                    "quarter": 4,
                    "rating": "bad",
                    "receipts": [
                        0.0,
                        0.0,
                        0.0
                    ],
                    "result": -0.0,
                    "year": 2016
                },
                {
                    "amount_type": "ACT",
                    "billing": [
                        0.0,
                        0.0,
                        0.0
                    ],
                    "date": "2016q3",
                    "month": 9,
                    "quarter": 3,
                    "rating": "bad",
                    "receipts": [
                        0.0,
                        0.0,
                        0.0
                    ],
                    "result": 0,
                    "year": 2016
                },
                {
                    "amount_type": "ACT",
                    "billing": [
                        0.0,
                        0.0,
                        0.0
                    ],
                    "date": "2016q2",
                    "month": 6,
                    "quarter": 2,
                    "rating": "bad",
                    "receipts": [
                        0.0,
                        0.0,
                        0.0
                    ],
                    "result": 0,
                    "year": 2016
                },
                {
                    "amount_type": "ACT",
                    "billing": [
                        0.0,
                        0.0,
                        0.0
                    ],
                    "date": "2016q1",
                    "month": 3,
                    "quarter": 1,
                    "rating": "bad",
                    "receipts": [
                        0.0,
                        0.0,
                        0.0
                    ],
                    "result": 0,
                    "year": 2016
                }
            ]
        },
        "current_ratio": {
            "ref": {
                "title": "Circular 71",
                "url": "http://mfma.treasury.gov.za/Circulars/Pages/Circular71.aspx"
            },
            "values": [
                {
                    "amount_type": "ACT",
                    "assets": 274038.0,
                    "date": "2017q1",
                    "liabilities": 4417269.0,
                    "month": 3,
                    "quarter": 1,
                    "rating": "bad",
                    "result": 0.06,
                    "year": 2017
                },
                {
                    "amount_type": "ACT",
                    "assets": 3785582.0,
                    "date": "2016q4",
                    "liabilities": 10692816.0,
                    "month": 12,
                    "quarter": 4,
                    "rating": "bad",
                    "result": 0.35,
                    "year": 2016
                },
                {
                    "amount_type": "ACT",
                    "assets": 16963938.0,
                    "date": "2016q3",
                    "liabilities": 3635014.0,
                    "month": 9,
                    "quarter": 3,
                    "rating": "good",
                    "result": 4.67,
                    "year": 2016
                },
                {
                    "amount_type": "ACT",
                    "assets": 3636276.0,
                    "date": "2016q2",
                    "liabilities": 6450848.0,
                    "month": 6,
                    "quarter": 2,
                    "rating": "bad",
                    "result": 0.56,
                    "year": 2016
                },
                {
                    "amount_type": "ACT",
                    "assets": 6722812.0,
                    "date": "2016q1",
                    "liabilities": 2210264.0,
                    "month": 3,
                    "quarter": 1,
                    "rating": "good",
                    "result": 3.04,
                    "year": 2016
                }
            ]
        },
        "expenditure_functional_breakdown": {
            "values": [
                {
                    "amount": 46595884.0,
                    "date": 2012,
                    "item": "Community & Social Services",
                    "percent": 47.24
                },
                {
                    "amount": 45414768.0,
                    "date": 2012,
                    "item": "Governance, Administration, Planning and Development",
                    "percent": 46.05
                },
                {
                    "amount": 1746338.0,
                    "date": 2012,
                    "item": "Health",
                    "percent": 1.77
                },
                {
                    "amount": 1703643.0,
                    "date": 2012,
                    "item": "Housing",
                    "percent": 1.73
                },
                {
                    "amount": 884914.0,
                    "date": 2012,
                    "item": "Other",
                    "percent": 0.9
                },
                {
                    "amount": 2283789.0,
                    "date": 2012,
                    "item": "Public Safety",
                    "percent": 2.32
                },
                {
                    "amount": 354.0,
                    "date": 2012,
                    "item": "Waste Management",
                    "percent": 0.0
                },
                {
                    "amount": 6008315.0,
                    "date": 2013,
                    "item": "Community & Social Services",
                    "percent": 10.26
                },
                {
                    "amount": 46345090.0,
                    "date": 2013,
                    "item": "Governance, Administration, Planning and Development",
                    "percent": 79.12
                },
                {
                    "amount": 1947898.0,
                    "date": 2013,
                    "item": "Health",
                    "percent": 3.33
                },
                {
                    "amount": 1958352.0,
                    "date": 2013,
                    "item": "Housing",
                    "percent": 3.34
                },
                {
                    "amount": 635153.0,
                    "date": 2013,
                    "item": "Other",
                    "percent": 1.08
                },
                {
                    "amount": 1680641.0,
                    "date": 2013,
                    "item": "Public Safety",
                    "percent": 2.87
                },
                {
                    "amount": 11681306.0,
                    "date": 2014,
                    "item": "Community & Social Services",
                    "percent": 18.46
                },
                {
                    "amount": 43904959.0,
                    "date": 2014,
                    "item": "Governance, Administration, Planning and Development",
                    "percent": 69.38
                },
                {
                    "amount": 2598543.0,
                    "date": 2014,
                    "item": "Health",
                    "percent": 4.11
                },
                {
                    "amount": 2234471.0,
                    "date": 2014,
                    "item": "Housing",
                    "percent": 3.53
                },
                {
                    "amount": 666953.0,
                    "date": 2014,
                    "item": "Other",
                    "percent": 1.05
                },
                {
                    "amount": 2193197.0,
                    "date": 2014,
                    "item": "Public Safety",
                    "percent": 3.47
                },
                {
                    "amount": 3998106.0,
                    "date": 2015,
                    "item": "Community & Social Services",
                    "percent": 6.83
                },
                {
                    "amount": 44637007.0,
                    "date": 2015,
                    "item": "Governance, Administration, Planning and Development",
                    "percent": 76.28
                },
                {
                    "amount": 2792921.0,
                    "date": 2015,
                    "item": "Health",
                    "percent": 4.77
                },
                {
                    "amount": 2723849.0,
                    "date": 2015,
                    "item": "Housing",
                    "percent": 4.65
                },
                {
                    "amount": 618211.0,
                    "date": 2015,
                    "item": "Other",
                    "percent": 1.06
                },
                {
                    "amount": 3744941.0,
                    "date": 2015,
                    "item": "Public Safety",
                    "percent": 6.4
                },
                {
                    "amount": 9731742.0,
                    "date": "2016 budget",
                    "item": "Community & Social Services",
                    "percent": 15.89
                },
                {
                    "amount": 44171431.0,
                    "date": "2016 budget",
                    "item": "Governance, Administration, Planning and Development",
                    "percent": 72.11
                },
                {
                    "amount": 2892079.0,
                    "date": "2016 budget",
                    "item": "Health",
                    "percent": 4.72
                },
                {
                    "amount": 1865131.0,
                    "date": "2016 budget",
                    "item": "Housing",
                    "percent": 3.05
                },
                {
                    "amount": 337300.0,
                    "date": "2016 budget",
                    "item": "Other",
                    "percent": 0.55
                },
                {
                    "amount": 2254379.0,
                    "date": "2016 budget",
                    "item": "Public Safety",
                    "percent": 3.68
                }
            ]
        },
        "expenditure_trends_contracting": {
            "values": [
                {
                    "date": 2015,
                    "rating": "",
                    "result": 0.05
                },
                {
                    "date": 2014,
                    "rating": "",
                    "result": 0.13
                },
                {
                    "date": 2013,
                    "rating": "",
                    "result": 1.98
                },
                {
                    "date": 2012,
                    "rating": "",
                    "result": 3.16
                }
            ]
        },
        "expenditure_trends_staff": {
            "values": [
                {
                    "date": 2015,
                    "rating": "",
                    "result": 66.12
                },
                {
                    "date": 2014,
                    "rating": "",
                    "result": 36.79
                },
                {
                    "date": 2013,
                    "rating": "",
                    "result": 58.35
                },
                {
                    "date": 2012,
                    "rating": "",
                    "result": 30.28
                }
            ]
        },
        "liquidity_ratio": {
            "ref": {
                "title": "Municipal Budget and Reporting Regulations",
                "url": "http://mfma.treasury.gov.za/RegulationsandGazettes/Municipal%20Budget%20and%20Reporting%20Regulations/Pages/default.aspx"
            },
            "values": [
                {
                    "amount_type": "ACT",
                    "call_investment_deposits": -1270000.0,
                    "cash": 1380385.0,
                    "date": "2017q1",
                    "liabilities": 4417269.0,
                    "month": 3,
                    "quarter": 1,
                    "rating": "bad",
                    "result": 0.02,
                    "year": 2017
                },
                {
                    "amount_type": "ACT",
                    "call_investment_deposits": 2644740.0,
                    "cash": 974275.0,
                    "date": "2016q4",
                    "liabilities": 10692816.0,
                    "month": 12,
                    "quarter": 4,
                    "rating": "bad",
                    "result": 0.34,
                    "year": 2016
                },
                {
                    "amount_type": "ACT",
                    "call_investment_deposits": 4644638.0,
                    "cash": 12131140.0,
                    "date": "2016q3",
                    "liabilities": 3635014.0,
                    "month": 9,
                    "quarter": 3,
                    "rating": "good",
                    "result": 4.62,
                    "year": 2016
                },
                {
                    "amount_type": "ACT",
                    "call_investment_deposits": -4057555.0,
                    "cash": 7509027.0,
                    "date": "2016q2",
                    "liabilities": 6450848.0,
                    "month": 6,
                    "quarter": 2,
                    "rating": "bad",
                    "result": 0.54,
                    "year": 2016
                },
                {
                    "amount_type": "ACT",
                    "call_investment_deposits": -3500000.0,
                    "cash": 10041108.0,
                    "date": "2016q1",
                    "liabilities": 2210264.0,
                    "month": 3,
                    "quarter": 1,
                    "rating": "good",
                    "result": 2.96,
                    "year": 2016
                }
            ]
        },
        "op_budget_diff": {
            "ref": {
                "title": "Over and under spending reports to parliament",
                "url": "http://mfma.treasury.gov.za/Media_Releases/Reports%20to%20Parliament/Pages/default.aspx"
            },
            "values": [
                {
                    "date": 2015,
                    "overunder": "over",
                    "rating": "good",
                    "result": 3.9
                },
                {
                    "date": 2014,
                    "overunder": "over",
                    "rating": "ave",
                    "result": 10.4
                },
                {
                    "date": 2013,
                    "overunder": "under",
                    "rating": "good",
                    "result": -4.3
                },
                {
                    "date": 2012,
                    "overunder": "over",
                    "rating": "bad",
                    "result": 103617.0
                }
            ]
        },
        "rep_maint_perc_ppe": {
            "ref": {
                "title": "Circular 71",
                "url": "http://mfma.treasury.gov.za/Circulars/Pages/Circular71.aspx"
            },
            "values": [
                {
                    "date": 2015,
                    "rating": "bad",
                    "result": 2.34
                },
                {
                    "date": 2014,
                    "rating": "bad",
                    "result": 3.03
                },
                {
                    "date": 2013,
                    "rating": "bad",
                    "result": 1.7
                },
                {
                    "date": 2012,
                    "rating": "bad",
                    "result": 1.99
                }
            ]
        },
        "revenue_breakdown": {
            "values": [
                {
                    "amount": 0.0,
                    "amount_type": "AUDA",
                    "date": 2015,
                    "item": "Property rates",
                    "percent": 0
                },
                {
                    "amount": 0.0,
                    "amount_type": "AUDA",
                    "date": 2015,
                    "item": "Service Charges",
                    "percent": 0
                },
                {
                    "amount": 44594.0,
                    "amount_type": "AUDA",
                    "date": 2015,
                    "item": "Rental income",
                    "percent": 0.08
                },
                {
                    "amount": 310097.0,
                    "amount_type": "AUDA",
                    "date": 2015,
                    "item": "Interest and investments",
                    "percent": 0.58
                },
                {
                    "amount": 0.0,
                    "amount_type": "AUDA",
                    "date": 2015,
                    "item": "Fines",
                    "percent": 0
                },
                {
                    "amount": 0.0,
                    "amount_type": "AUDA",
                    "date": 2015,
                    "item": "Licenses and Permits",
                    "percent": 0
                },
                {
                    "amount": 0.0,
                    "amount_type": "AUDA",
                    "date": 2015,
                    "item": "Agency services",
                    "percent": 0
                },
                {
                    "amount": 51331435.0,
                    "amount_type": "AUDA",
                    "date": 2015,
                    "item": "Government Transfers for Operating Expenses",
                    "percent": 96.03
                },
                {
                    "amount": 0.0,
                    "amount_type": "AUDA",
                    "date": 2015,
                    "item": "Government Transfers for Capital Expenses",
                    "percent": 0
                },
                {
                    "amount": 594156.0,
                    "amount_type": "AUDA",
                    "date": 2015,
                    "item": "Other",
                    "percent": 1.11
                },
                {
                    "amount": 0.0,
                    "amount_type": "AUDA",
                    "date": 2014,
                    "item": "Property rates",
                    "percent": 0
                },
                {
                    "amount": 0.0,
                    "amount_type": "AUDA",
                    "date": 2014,
                    "item": "Service Charges",
                    "percent": 0
                },
                {
                    "amount": 33348.0,
                    "amount_type": "AUDA",
                    "date": 2014,
                    "item": "Rental income",
                    "percent": 0.06
                },
                {
                    "amount": 675996.0,
                    "amount_type": "AUDA",
                    "date": 2014,
                    "item": "Interest and investments",
                    "percent": 1.24
                },
                {
                    "amount": 0.0,
                    "amount_type": "AUDA",
                    "date": 2014,
                    "item": "Fines",
                    "percent": 0
                },
                {
                    "amount": 0.0,
                    "amount_type": "AUDA",
                    "date": 2014,
                    "item": "Licenses and Permits",
                    "percent": 0
                },
                {
                    "amount": 0.0,
                    "amount_type": "AUDA",
                    "date": 2014,
                    "item": "Agency services",
                    "percent": 0
                },
                {
                    "amount": 49534878.0,
                    "amount_type": "AUDA",
                    "date": 2014,
                    "item": "Government Transfers for Operating Expenses",
                    "percent": 91.02
                },
                {
                    "amount": 716569.0,
                    "amount_type": "AUDA",
                    "date": 2014,
                    "item": "Government Transfers for Capital Expenses",
                    "percent": 1.32
                },
                {
                    "amount": 3461626.0,
                    "amount_type": "AUDA",
                    "date": 2014,
                    "item": "Other",
                    "percent": 6.36
                },
                {
                    "amount": 0.0,
                    "amount_type": "AUDA",
                    "date": 2013,
                    "item": "Property rates",
                    "percent": 0
                },
                {
                    "amount": 0.0,
                    "amount_type": "AUDA",
                    "date": 2013,
                    "item": "Service Charges",
                    "percent": 0
                },
                {
                    "amount": 141070.0,
                    "amount_type": "AUDA",
                    "date": 2013,
                    "item": "Rental income",
                    "percent": 0.23
                },
                {
                    "amount": 305566.0,
                    "amount_type": "AUDA",
                    "date": 2013,
                    "item": "Interest and investments",
                    "percent": 0.49
                },
                {
                    "amount": 0.0,
                    "amount_type": "AUDA",
                    "date": 2013,
                    "item": "Fines",
                    "percent": 0
                },
                {
                    "amount": 0.0,
                    "amount_type": "AUDA",
                    "date": 2013,
                    "item": "Licenses and Permits",
                    "percent": 0
                },
                {
                    "amount": 0.0,
                    "amount_type": "AUDA",
                    "date": 2013,
                    "item": "Agency services",
                    "percent": 0
                },
                {
                    "amount": 49905426.0,
                    "amount_type": "AUDA",
                    "date": 2013,
                    "item": "Government Transfers for Operating Expenses",
                    "percent": 80.68
                },
                {
                    "amount": 8985078.0,
                    "amount_type": "AUDA",
                    "date": 2013,
                    "item": "Government Transfers for Capital Expenses",
                    "percent": 14.53
                },
                {
                    "amount": 2516745.0,
                    "amount_type": "AUDA",
                    "date": 2013,
                    "item": "Other",
                    "percent": 4.07
                },
                {
                    "amount": 0.0,
                    "amount_type": "AUDA",
                    "date": 2012,
                    "item": "Property rates",
                    "percent": 0
                },
                {
                    "amount": 0.0,
                    "amount_type": "AUDA",
                    "date": 2012,
                    "item": "Service Charges",
                    "percent": 0
                },
                {
                    "amount": 8625.0,
                    "amount_type": "AUDA",
                    "date": 2012,
                    "item": "Rental income",
                    "percent": 0.01
                },
                {
                    "amount": 535796.0,
                    "amount_type": "AUDA",
                    "date": 2012,
                    "item": "Interest and investments",
                    "percent": 0.88
                },
                {
                    "amount": 0.0,
                    "amount_type": "AUDA",
                    "date": 2012,
                    "item": "Fines",
                    "percent": 0
                },
                {
                    "amount": 0.0,
                    "amount_type": "AUDA",
                    "date": 2012,
                    "item": "Licenses and Permits",
                    "percent": 0
                },
                {
                    "amount": 0.0,
                    "amount_type": "AUDA",
                    "date": 2012,
                    "item": "Agency services",
                    "percent": 0
                },
                {
                    "amount": 44168577.0,
                    "amount_type": "AUDA",
                    "date": 2012,
                    "item": "Government Transfers for Operating Expenses",
                    "percent": 72.26
                },
                {
                    "amount": 9981700.0,
                    "amount_type": "AUDA",
                    "date": 2012,
                    "item": "Government Transfers for Capital Expenses",
                    "percent": 16.33
                },
                {
                    "amount": 6428743.0,
                    "amount_type": "AUDA",
                    "date": 2012,
                    "item": "Other",
                    "percent": 10.52
                },
                {
                    "amount": 0.0,
                    "amount_type": "ORGB",
                    "date": "2016 budget",
                    "item": "Property rates",
                    "percent": 0
                },
                {
                    "amount": 0.0,
                    "amount_type": "ORGB",
                    "date": "2016 budget",
                    "item": "Service Charges",
                    "percent": 0
                },
                {
                    "amount": 85000.0,
                    "amount_type": "ORGB",
                    "date": "2016 budget",
                    "item": "Rental income",
                    "percent": 0.14
                },
                {
                    "amount": 350000.0,
                    "amount_type": "ORGB",
                    "date": "2016 budget",
                    "item": "Interest and investments",
                    "percent": 0.56
                },
                {
                    "amount": 0.0,
                    "amount_type": "ORGB",
                    "date": "2016 budget",
                    "item": "Fines",
                    "percent": 0
                },
                {
                    "amount": 0.0,
                    "amount_type": "ORGB",
                    "date": "2016 budget",
                    "item": "Licenses and Permits",
                    "percent": 0
                },
                {
                    "amount": 0.0,
                    "amount_type": "ORGB",
                    "date": "2016 budget",
                    "item": "Agency services",
                    "percent": 0
                },
                {
                    "amount": 56464000.0,
                    "amount_type": "ORGB",
                    "date": "2016 budget",
                    "item": "Government Transfers for Operating Expenses",
                    "percent": 90.29
                },
                {
                    "amount": 0.0,
                    "amount_type": "ORGB",
                    "date": "2016 budget",
                    "item": "Government Transfers for Capital Expenses",
                    "percent": 0
                },
                {
                    "amount": 5635000.0,
                    "amount_type": "ORGB",
                    "date": "2016 budget",
                    "item": "Other",
                    "percent": 9.01
                }
            ]
        },
        "revenue_sources": {
            "government": {
                "amount": 51331435.0,
                "items": [
                    {
                        "amount.sum": 51331435.0,
                        "amount_type.code": "AUDA",
                        "financial_year_end.year": 2015,
                        "item.code": "1600",
                        "item.label": "Transfers Recognised - Operating"
                    },
                    {
                        "amount.sum": 0.0,
                        "amount_type.code": "AUDA",
                        "financial_year_end.year": 2015,
                        "item.code": "1610",
                        "item.label": "Transfers Recognised - Capital"
                    }
                ],
                "percent": 96.03
            },
            "local": {
                "amount": 948847.0,
                "items": [
                    {
                        "amount.sum": 0.0,
                        "amount_type.code": "AUDA",
                        "financial_year_end.year": 2015,
                        "item.code": "0200",
                        "item.label": "Property Rates"
                    },
                    {
                        "amount.sum": 0.0,
                        "amount_type.code": "AUDA",
                        "financial_year_end.year": 2015,
                        "item.code": "0300",
                        "item.label": "Property Rates - Penalties And Collection Charges"
                    },
                    {
                        "amount.sum": 0.0,
                        "amount_type.code": "AUDA",
                        "financial_year_end.year": 2015,
                        "item.code": "0400",
                        "item.label": "Service Charges"
                    },
                    {
                        "amount.sum": 44594.0,
                        "amount_type.code": "AUDA",
                        "financial_year_end.year": 2015,
                        "item.code": "0700",
                        "item.label": "Rent Of Facilities And Equipment"
                    },
                    {
                        "amount.sum": 305804.0,
                        "amount_type.code": "AUDA",
                        "financial_year_end.year": 2015,
                        "item.code": "0800",
                        "item.label": "Interest Earned - External Investments"
                    },
                    {
                        "amount.sum": 4293.0,
                        "amount_type.code": "AUDA",
                        "financial_year_end.year": 2015,
                        "item.code": "1000",
                        "item.label": "Interest Earned - Outstanding Debtors"
                    },
                    {
                        "amount.sum": 0.0,
                        "amount_type.code": "AUDA",
                        "financial_year_end.year": 2015,
                        "item.code": "1100",
                        "item.label": "Dividends Received"
                    },
                    {
                        "amount.sum": 0.0,
                        "amount_type.code": "AUDA",
                        "financial_year_end.year": 2015,
                        "item.code": "1300",
                        "item.label": "Fines"
                    },
                    {
                        "amount.sum": 0.0,
                        "amount_type.code": "AUDA",
                        "financial_year_end.year": 2015,
                        "item.code": "1400",
                        "item.label": "Licenses and Permits"
                    },
                    {
                        "amount.sum": 0.0,
                        "amount_type.code": "AUDA",
                        "financial_year_end.year": 2015,
                        "item.code": "1500",
                        "item.label": "Agency Services"
                    },
                    {
                        "amount.sum": 594156.0,
                        "amount_type.code": "AUDA",
                        "financial_year_end.year": 2015,
                        "item.code": "1700",
                        "item.label": "Other Revenue"
                    },
                    {
                        "amount.sum": 0.0,
                        "amount_type.code": "AUDA",
                        "financial_year_end.year": 2015,
                        "item.code": "1800",
                        "item.label": "Gain On Disposal Of Property, Plant & Equipment"
                    }
                ],
                "percent": 1.78
            },
            "rating": "bad",
            "ref": {
                "title": "Local Government Equitable Share",
                "url": "http://mfma.treasury.gov.za/Media_Releases/LGESDiscussions/Pages/default.aspx"
            },
            "year": 2015
        },
        "wasteful_exp": {
            "ref": {
                "title": "Circular 71",
                "url": "http://mfma.treasury.gov.za/Circulars/Pages/Circular71.aspx"
            },
            "values": [
                {
                    "date": 2015,
                    "rating": null,
                    "result": null
                },
                {
                    "date": 2014,
                    "rating": "bad",
                    "result": 10.83
                },
                {
                    "date": 2013,
                    "rating": "bad",
                    "result": 6.76
                },
                {
                    "date": 2012,
                    "rating": "bad",
                    "result": 20.2
                }
            ]
        }
    },
    "mayoral_staff": {
        "officials": [
            {
                "email": "avosloo@zfm-dm.gov.za",
                "fax_number": "054 337 2888",
                "name": "Abraham Vosloo",
                "office_phone": "054 337 2838",
                "role": "Mayor/Executive Mayor",
                "secretary": {
                    "email": "drapatsa@zfm-dm.gov.za",
                    "fax_number": "054 337 2888",
                    "name": "Denise Rapatsa",
                    "office_phone": "054 337 2838",
                    "role": "Secretary of Mayor/Executive Mayor",
                    "title": "Mrs"
                },
                "title": "Mr"
            },
            {
                "email": "entoba@zfm-dm.gov.za",
                "fax_number": "054 337 2888",
                "name": "Elias Ntoba",
                "office_phone": "054 337 2868",
                "role": "Municipal Manager",
                "secretary": {
                    "email": "sc@zfm-dm.gov.za",
                    "fax_number": "054 337 2888",
                    "name": "Suzzelle Coetzee",
                    "office_phone": "054 337 2868",
                    "role": "Secretary of Municipal Manager",
                    "title": "Ms"
                },
                "title": "Mr"
            },
            {
                "email": null,
                "fax_number": null,
                "name": null,
                "office_phone": null,
                "role": "Deputy Mayor/Executive Mayor",
                "title": null
            },
            {
                "email": "pb@zfm-dm.gov.za",
                "fax_number": "054 337 2888",
                "name": "P Beukes",
                "office_phone": "054 337 2800",
                "role": "Chief Financial Officer",
                "secretary": {
                    "email": "clj@siyanda.gov.za",
                    "fax_number": "054 337 2800",
                    "name": "C. Job",
                    "office_phone": "054 337 2816",
                    "role": "Secretary of Financial Manager",
                    "title": "Ms"
                },
                "title": "Mr"
            }
        ],
        "updated_date": "December 2016"
    },
    "muni_contact": {
        "phone_number": "054 337 2800",
        "street_address_1": "Cnr Hill & Le Roux Street",
        "street_address_2": "C/o Upington 26 & Nelson Mandela Drive",
        "street_address_3": "UPINGTON",
        "street_address_4": "8800",
        "url": "http://www.zfm-dm.gov.za"
    }
}