{
    "audit_opinions": {
        "values": [
            {
                "date": 2018,
                "rating": "qualified",
                "report_url": "http://mfma.treasury.gov.za/Documents/07.%20Audit%20Reports/2017-18/02.%20Local%20municipalities/FS196%20Mantsopa/FS196%20Mantsopa%20Audit%20report%202017-18.pdf",
                "result": "Qualified"
            },
            {
                "date": 2017,
                "rating": "qualified",
                "report_url": "http://mfma.treasury.gov.za/Documents/07.%20Audit%20Reports/2016-17/02.%20Local%20municipalities/FS196%20Mantsopa/FS196%20Mantsopa%20Audit%20report%202016-17.pdf",
                "result": "Qualified"
            },
            {
                "date": 2016,
                "rating": "qualified",
                "report_url": "http://mfma.treasury.gov.za/Documents/07.%20Audit%20Reports/2015-16/02.%20Local%20municipalities/FS196%20Mantsopa/FS196%20Mantsopa%20Audit%20report%202015-16.pdf",
                "result": "Qualified"
            },
            {
                "date": 2015,
                "rating": "qualified",
                "report_url": "http://mfma.treasury.gov.za/Documents/07.%20Audit%20Reports/2014-15/02.%20Local%20municipalities/FS196%20Mantsopa/FS196%20Mantsopa%20Audit%20report%202014-15.pdf",
                "result": "Qualified"
            }
        ]
    },
    "demarcation": {
        "land_gained": [],
        "land_lost": []
    },
    "indicators": {
        "cap_budget_diff": {
            "ref": {
                "title": "Over and under spending reports to parliament",
                "url": "http://mfma.treasury.gov.za/Media_Releases/Reports%20to%20Parliament/Pages/default.aspx"
            },
            "values": [
                {
                    "date": 2018,
                    "overunder": "under",
                    "rating": "ave",
                    "result": -9.17
                },
                {
                    "date": 2017,
                    "overunder": "over",
                    "rating": "bad",
                    "result": 15.14
                },
                {
                    "date": 2016,
                    "overunder": "over",
                    "rating": "bad",
                    "result": 42.41
                },
                {
                    "date": 2015,
                    "overunder": "over",
                    "rating": "bad",
                    "result": 139.98
                }
            ]
        },
        "cash_at_year_end": {
            "ref": {
                "title": "State of Local Government Finances",
                "url": "http://mfma.treasury.gov.za/Media_Releases/The%20state%20of%20local%20government%20finances/Pages/default.aspx"
            },
            "values": [
                {
                    "date": 2018,
                    "rating": "good",
                    "result": 3529470.0
                },
                {
                    "date": 2017,
                    "rating": "good",
                    "result": 1187212.0
                },
                {
                    "date": 2016,
                    "rating": "good",
                    "result": 986752.0
                },
                {
                    "date": 2015,
                    "rating": "good",
                    "result": 7197621.0
                }
            ]
        },
        "cash_coverage": {
            "ref": {
                "title": "State of Local Government Finances",
                "url": "http://mfma.treasury.gov.za/Media_Releases/The%20state%20of%20local%20government%20finances/Pages/default.aspx"
            },
            "values": [
                {
                    "date": 2018,
                    "rating": "bad",
                    "result": 0.1
                },
                {
                    "date": 2017,
                    "rating": "bad",
                    "result": 0.0
                },
                {
                    "date": 2016,
                    "rating": "bad",
                    "result": 0.0
                },
                {
                    "date": 2015,
                    "rating": "bad",
                    "result": 0.3
                }
            ]
        },
        "current_debtors_collection_rate": {
            "ref": {
                "title": "Municipal Budget and Reporting Regulations",
                "url": "http://mfma.treasury.gov.za/RegulationsandGazettes/Municipal%20Budget%20and%20Reporting%20Regulations/Pages/default.aspx"
            },
            "values": [
                {
                    "amount_type": "ACT",
                    "billing": [
                        7245848.0,
                        8642495.0
                    ],
                    "date": "2019q3",
                    "month": 8,
                    "quarter": 3,
                    "rating": "bad",
                    "receipts": [
                        8688295.0,
                        9077219.0
                    ],
                    "result": null,
                    "year": 2019
                },
                {
                    "amount_type": "ACT",
                    "billing": [
                        7910284.0,
                        9645664.0,
                        7983875.0
                    ],
                    "date": "2019q2",
                    "month": 6,
                    "quarter": 2,
                    "rating": "bad",
                    "receipts": [
                        1993397.0,
                        4372917.0,
                        7699050.0
                    ],
                    "result": 55.07,
                    "year": 2019
                },
                {
                    "amount_type": "ACT",
                    "billing": [
                        9804167.0,
                        24779502.0,
                        9618897.0
                    ],
                    "date": "2019q1",
                    "month": 3,
                    "quarter": 1,
                    "rating": "bad",
                    "receipts": [
                        7106874.0,
                        4839753.0,
                        8367392.0
                    ],
                    "result": 45.96,
                    "year": 2019
                },
                {
                    "amount_type": "ACT",
                    "billing": [
                        11164901.0,
                        10763000.0,
                        11016905.0
                    ],
                    "date": "2018q4",
                    "month": 12,
                    "quarter": 4,
                    "rating": "bad",
                    "receipts": [
                        5199787.0,
                        5906058.0,
                        8693202.0
                    ],
                    "result": 60.1,
                    "year": 2018
                },
                {
                    "amount_type": "ACT",
                    "billing": [
                        10361189.0,
                        12967436.0,
                        10215305.0
                    ],
                    "date": "2018q3",
                    "month": 9,
                    "quarter": 3,
                    "rating": "bad",
                    "receipts": [
                        6750385.0,
                        6298449.0,
                        4882414.0
                    ],
                    "result": 53.46,
                    "year": 2018
                }
            ]
        },
        "current_ratio": {
            "ref": {
                "title": "Circular 71",
                "url": "http://mfma.treasury.gov.za/Circulars/Pages/Circular71.aspx"
            },
            "values": [
                {
                    "amount_type": "ACT",
                    "assets": 149962225.0,
                    "date": "2019q3",
                    "liabilities": 282137868.0,
                    "month": 9,
                    "quarter": 3,
                    "rating": "bad",
                    "result": 0.53,
                    "year": 2019
                },
                {
                    "amount_type": "ACT",
                    "assets": 117787750.0,
                    "date": "2019q2",
                    "liabilities": 280438653.0,
                    "month": 6,
                    "quarter": 2,
                    "rating": "bad",
                    "result": 0.42,
                    "year": 2019
                },
                {
                    "amount_type": "ACT",
                    "assets": 123132480.0,
                    "date": "2019q1",
                    "liabilities": 278139571.0,
                    "month": 3,
                    "quarter": 1,
                    "rating": "bad",
                    "result": 0.44,
                    "year": 2019
                },
                {
                    "amount_type": "ACT",
                    "assets": 589512762.0,
                    "date": "2018q4",
                    "liabilities": 180849232.0,
                    "month": 12,
                    "quarter": 4,
                    "rating": "good",
                    "result": 3.26,
                    "year": 2018
                },
                {
                    "amount_type": "ACT",
                    "assets": 237850023.0,
                    "date": "2018q3",
                    "liabilities": 213480610.0,
                    "month": 9,
                    "quarter": 3,
                    "rating": "ave",
                    "result": 1.11,
                    "year": 2018
                }
            ]
        },
        "expenditure_functional_breakdown": {
            "values": [
                {
                    "amount": 11766494.0,
                    "date": "2015",
                    "item": "Community & Social Services",
                    "percent": 4.22
                },
                {
                    "amount": 53878469.0,
                    "date": "2015",
                    "item": "Electricity ",
                    "percent": 19.31
                },
                {
                    "amount": 71310325.0,
                    "date": "2015",
                    "item": "Governance, Administration, Planning and Development",
                    "percent": 25.56
                },
                {
                    "amount": 1575508.0,
                    "date": "2015",
                    "item": "Housing",
                    "percent": 0.56
                },
                {
                    "amount": 3517155.0,
                    "date": "2015",
                    "item": "Public Safety",
                    "percent": 1.26
                },
                {
                    "amount": 50370634.0,
                    "date": "2015",
                    "item": "Road Transport",
                    "percent": 18.05
                },
                {
                    "amount": 4565844.0,
                    "date": "2015",
                    "item": "Sport And Recreation",
                    "percent": 1.64
                },
                {
                    "amount": 25439173.0,
                    "date": "2015",
                    "item": "Waste Management",
                    "percent": 9.12
                },
                {
                    "amount": 34129254.0,
                    "date": "2015",
                    "item": "Waste Water Management",
                    "percent": 12.23
                },
                {
                    "amount": 22463806.0,
                    "date": "2015",
                    "item": "Water",
                    "percent": 8.05
                },
                {
                    "amount": 8452792.0,
                    "date": "2016",
                    "item": "Community & Social Services",
                    "percent": 3.31
                },
                {
                    "amount": 43578510.0,
                    "date": "2016",
                    "item": "Electricity ",
                    "percent": 17.08
                },
                {
                    "amount": 71032220.0,
                    "date": "2016",
                    "item": "Governance, Administration, Planning and Development",
                    "percent": 27.84
                },
                {
                    "amount": 1705961.0,
                    "date": "2016",
                    "item": "Housing",
                    "percent": 0.67
                },
                {
                    "amount": 3902301.0,
                    "date": "2016",
                    "item": "Public Safety",
                    "percent": 1.53
                },
                {
                    "amount": 33319387.0,
                    "date": "2016",
                    "item": "Road Transport",
                    "percent": 13.06
                },
                {
                    "amount": 4580024.0,
                    "date": "2016",
                    "item": "Sport And Recreation",
                    "percent": 1.79
                },
                {
                    "amount": 10839585.0,
                    "date": "2016",
                    "item": "Waste Management",
                    "percent": 4.25
                },
                {
                    "amount": 23426206.0,
                    "date": "2016",
                    "item": "Waste Water Management",
                    "percent": 9.18
                },
                {
                    "amount": 54327130.0,
                    "date": "2016",
                    "item": "Water",
                    "percent": 21.29
                },
                {
                    "amount": 7855361.0,
                    "date": "2017",
                    "item": "Community & Social Services",
                    "percent": 2.66
                },
                {
                    "amount": 43399426.0,
                    "date": "2017",
                    "item": "Electricity ",
                    "percent": 14.71
                },
                {
                    "amount": 92891971.0,
                    "date": "2017",
                    "item": "Governance, Administration, Planning and Development",
                    "percent": 31.49
                },
                {
                    "amount": 1704360.0,
                    "date": "2017",
                    "item": "Housing",
                    "percent": 0.58
                },
                {
                    "amount": 3759199.0,
                    "date": "2017",
                    "item": "Public Safety",
                    "percent": 1.27
                },
                {
                    "amount": 96537990.0,
                    "date": "2017",
                    "item": "Road Transport",
                    "percent": 32.72
                },
                {
                    "amount": 5320822.0,
                    "date": "2017",
                    "item": "Sport And Recreation",
                    "percent": 1.8
                },
                {
                    "amount": -3534319.0,
                    "date": "2017",
                    "item": "Waste Management",
                    "percent": -1.2
                },
                {
                    "amount": 22986762.0,
                    "date": "2017",
                    "item": "Waste Water Management",
                    "percent": 7.79
                },
                {
                    "amount": 24092470.0,
                    "date": "2017",
                    "item": "Water",
                    "percent": 8.17
                },
                {
                    "amount": 4281657.0,
                    "date": "2018",
                    "item": "Community & Social Services",
                    "percent": 1.08
                },
                {
                    "amount": 42798076.0,
                    "date": "2018",
                    "item": "Electricity ",
                    "percent": 10.84
                },
                {
                    "amount": 276653157.0,
                    "date": "2018",
                    "item": "Governance, Administration, Planning and Development",
                    "percent": 70.04
                },
                {
                    "amount": 3362804.0,
                    "date": "2018",
                    "item": "Housing",
                    "percent": 0.85
                },
                {
                    "amount": 5014805.0,
                    "date": "2018",
                    "item": "Public Safety",
                    "percent": 1.27
                },
                {
                    "amount": 6094742.0,
                    "date": "2018",
                    "item": "Road Transport",
                    "percent": 1.54
                },
                {
                    "amount": 10706238.0,
                    "date": "2018",
                    "item": "Waste Management",
                    "percent": 2.71
                },
                {
                    "amount": 10861720.0,
                    "date": "2018",
                    "item": "Waste Water Management",
                    "percent": 2.75
                },
                {
                    "amount": 35199207.0,
                    "date": "2018",
                    "item": "Water",
                    "percent": 8.91
                },
                {
                    "amount": 2699324.0,
                    "date": "2019 budget",
                    "item": "Community & Social Services",
                    "percent": 1.17
                },
                {
                    "amount": 44373913.0,
                    "date": "2019 budget",
                    "item": "Electricity ",
                    "percent": 19.31
                },
                {
                    "amount": 91624982.0,
                    "date": "2019 budget",
                    "item": "Governance, Administration, Planning and Development",
                    "percent": 39.87
                },
                {
                    "amount": 2742658.0,
                    "date": "2019 budget",
                    "item": "Housing",
                    "percent": 1.19
                },
                {
                    "amount": 8388845.0,
                    "date": "2019 budget",
                    "item": "Public Safety",
                    "percent": 3.65
                },
                {
                    "amount": 16065328.0,
                    "date": "2019 budget",
                    "item": "Road Transport",
                    "percent": 6.99
                },
                {
                    "amount": 4624426.0,
                    "date": "2019 budget",
                    "item": "Sport And Recreation",
                    "percent": 2.01
                },
                {
                    "amount": 17191941.0,
                    "date": "2019 budget",
                    "item": "Waste Management",
                    "percent": 7.48
                },
                {
                    "amount": 16521959.0,
                    "date": "2019 budget",
                    "item": "Waste Water Management",
                    "percent": 7.19
                },
                {
                    "amount": 25554226.0,
                    "date": "2019 budget",
                    "item": "Water",
                    "percent": 11.12
                }
            ]
        },
        "expenditure_trends_contracting": {
            "values": [
                {
                    "date": 2018,
                    "rating": "",
                    "result": 0.29
                },
                {
                    "date": 2017,
                    "rating": "",
                    "result": 0.28
                },
                {
                    "date": 2016,
                    "rating": "",
                    "result": 0.39
                },
                {
                    "date": 2015,
                    "rating": "",
                    "result": 1.12
                }
            ]
        },
        "expenditure_trends_staff": {
            "values": [
                {
                    "date": 2018,
                    "rating": "",
                    "result": 21.26
                },
                {
                    "date": 2017,
                    "rating": "",
                    "result": 26.48
                },
                {
                    "date": 2016,
                    "rating": "",
                    "result": 30.78
                },
                {
                    "date": 2015,
                    "rating": "",
                    "result": 24.52
                }
            ]
        },
        "liquidity_ratio": {
            "ref": {
                "title": "Municipal Budget and Reporting Regulations",
                "url": "http://mfma.treasury.gov.za/RegulationsandGazettes/Municipal%20Budget%20and%20Reporting%20Regulations/Pages/default.aspx"
            },
            "values": [
                {
                    "amount_type": "ACT",
                    "call_investment_deposits": 202796.0,
                    "cash": 13360959.0,
                    "date": "2019q3",
                    "liabilities": 282137868.0,
                    "month": 9,
                    "quarter": 3,
                    "rating": "bad",
                    "result": 0.05,
                    "year": 2019
                },
                {
                    "amount_type": "ACT",
                    "call_investment_deposits": 197109.0,
                    "cash": 4033628.0,
                    "date": "2019q2",
                    "liabilities": 280438653.0,
                    "month": 6,
                    "quarter": 2,
                    "rating": "bad",
                    "result": 0.02,
                    "year": 2019
                },
                {
                    "amount_type": "ACT",
                    "call_investment_deposits": 13605501.0,
                    "cash": 1564.0,
                    "date": "2019q1",
                    "liabilities": 278139571.0,
                    "month": 3,
                    "quarter": 1,
                    "rating": "bad",
                    "result": 0.05,
                    "year": 2019
                },
                {
                    "amount_type": "ACT",
                    "call_investment_deposits": 2722410.0,
                    "cash": 1563.0,
                    "date": "2018q4",
                    "liabilities": 180849232.0,
                    "month": 12,
                    "quarter": 4,
                    "rating": "bad",
                    "result": 0.02,
                    "year": 2018
                },
                {
                    "amount_type": "ACT",
                    "call_investment_deposits": 9876505.0,
                    "cash": 2989.0,
                    "date": "2018q3",
                    "liabilities": 213480610.0,
                    "month": 9,
                    "quarter": 3,
                    "rating": "bad",
                    "result": 0.05,
                    "year": 2018
                }
            ]
        },
        "op_budget_diff": {
            "ref": {
                "title": "Over and under spending reports to parliament",
                "url": "http://mfma.treasury.gov.za/Media_Releases/Reports%20to%20Parliament/Pages/default.aspx"
            },
            "values": [
                {
                    "date": 2018,
                    "overunder": "over",
                    "rating": "bad",
                    "result": 73.2
                },
                {
                    "date": 2017,
                    "overunder": "over",
                    "rating": "bad",
                    "result": 47.9
                },
                {
                    "date": 2016,
                    "overunder": "over",
                    "rating": "ave",
                    "result": 9.8
                },
                {
                    "date": 2015,
                    "overunder": "over",
                    "rating": "bad",
                    "result": 33.4
                }
            ]
        },
        "rep_maint_perc_ppe": {
            "ref": {
                "title": "Circular 71",
                "url": "http://mfma.treasury.gov.za/Circulars/Pages/Circular71.aspx"
            },
            "values": [
                {
                    "date": 2018,
                    "rating": "bad",
                    "result": 0.0
                },
                {
                    "date": 2017,
                    "rating": "bad",
                    "result": 0.0
                },
                {
                    "date": 2016,
                    "rating": "bad",
                    "result": 0.66
                },
                {
                    "date": 2015,
                    "rating": "bad",
                    "result": 0.76
                }
            ]
        },
        "revenue_breakdown": {
            "values": [
                {
                    "amount": 13931288.0,
                    "amount_type": "AUDA",
                    "date": "2018",
                    "item": "Property rates",
                    "percent": 4.88
                },
                {
                    "amount": 117706855.0,
                    "amount_type": "AUDA",
                    "date": "2018",
                    "item": "Service Charges",
                    "percent": 41.26
                },
                {
                    "amount": 0.0,
                    "amount_type": "AUDA",
                    "date": "2018",
                    "item": "Rental income",
                    "percent": 0
                },
                {
                    "amount": 28147151.0,
                    "amount_type": "AUDA",
                    "date": "2018",
                    "item": "Interest and investments",
                    "percent": 9.87
                },
                {
                    "amount": 527300.0,
                    "amount_type": "AUDA",
                    "date": "2018",
                    "item": "Fines",
                    "percent": 0.18
                },
                {
                    "amount": 0.0,
                    "amount_type": "AUDA",
                    "date": "2018",
                    "item": "Licenses and Permits",
                    "percent": 0
                },
                {
                    "amount": 0.0,
                    "amount_type": "AUDA",
                    "date": "2018",
                    "item": "Agency services",
                    "percent": 0
                },
                {
                    "amount": 72416619.0,
                    "amount_type": "AUDA",
                    "date": "2018",
                    "item": "Government Transfers for Operating Expenses",
                    "percent": 25.39
                },
                {
                    "amount": 41777573.0,
                    "amount_type": "AUDA",
                    "date": "2018",
                    "item": "Government Transfers for Capital Expenses",
                    "percent": 14.64
                },
                {
                    "amount": 10764251.0,
                    "amount_type": "AUDA",
                    "date": "2018",
                    "item": "Other",
                    "percent": 3.77
                },
                {
                    "amount": 12145428.0,
                    "amount_type": "AUDA",
                    "date": "2017",
                    "item": "Property rates",
                    "percent": 4.17
                },
                {
                    "amount": 113156670.0,
                    "amount_type": "AUDA",
                    "date": "2017",
                    "item": "Service Charges",
                    "percent": 38.81
                },
                {
                    "amount": 0.0,
                    "amount_type": "AUDA",
                    "date": "2017",
                    "item": "Rental income",
                    "percent": 0
                },
                {
                    "amount": 24546080.0,
                    "amount_type": "AUDA",
                    "date": "2017",
                    "item": "Interest and investments",
                    "percent": 8.42
                },
                {
                    "amount": 598630.0,
                    "amount_type": "AUDA",
                    "date": "2017",
                    "item": "Fines",
                    "percent": 0.21
                },
                {
                    "amount": 0.0,
                    "amount_type": "AUDA",
                    "date": "2017",
                    "item": "Licenses and Permits",
                    "percent": 0
                },
                {
                    "amount": 0.0,
                    "amount_type": "AUDA",
                    "date": "2017",
                    "item": "Agency services",
                    "percent": 0
                },
                {
                    "amount": 70557925.0,
                    "amount_type": "AUDA",
                    "date": "2017",
                    "item": "Government Transfers for Operating Expenses",
                    "percent": 24.2
                },
                {
                    "amount": 68046925.0,
                    "amount_type": "AUDA",
                    "date": "2017",
                    "item": "Government Transfers for Capital Expenses",
                    "percent": 23.34
                },
                {
                    "amount": 2551082.0,
                    "amount_type": "AUDA",
                    "date": "2017",
                    "item": "Other",
                    "percent": 0.87
                },
                {
                    "amount": 15363209.0,
                    "amount_type": "AUDA",
                    "date": "2016",
                    "item": "Property rates",
                    "percent": 5.47
                },
                {
                    "amount": 93725816.0,
                    "amount_type": "AUDA",
                    "date": "2016",
                    "item": "Service Charges",
                    "percent": 33.35
                },
                {
                    "amount": 0.0,
                    "amount_type": "AUDA",
                    "date": "2016",
                    "item": "Rental income",
                    "percent": 0
                },
                {
                    "amount": 20015385.0,
                    "amount_type": "AUDA",
                    "date": "2016",
                    "item": "Interest and investments",
                    "percent": 7.12
                },
                {
                    "amount": 522550.0,
                    "amount_type": "AUDA",
                    "date": "2016",
                    "item": "Fines",
                    "percent": 0.19
                },
                {
                    "amount": 0.0,
                    "amount_type": "AUDA",
                    "date": "2016",
                    "item": "Licenses and Permits",
                    "percent": 0
                },
                {
                    "amount": 0.0,
                    "amount_type": "AUDA",
                    "date": "2016",
                    "item": "Agency services",
                    "percent": 0
                },
                {
                    "amount": 72778636.0,
                    "amount_type": "AUDA",
                    "date": "2016",
                    "item": "Government Transfers for Operating Expenses",
                    "percent": 25.9
                },
                {
                    "amount": 71241514.0,
                    "amount_type": "AUDA",
                    "date": "2016",
                    "item": "Government Transfers for Capital Expenses",
                    "percent": 25.35
                },
                {
                    "amount": 7373890.0,
                    "amount_type": "AUDA",
                    "date": "2016",
                    "item": "Other",
                    "percent": 2.62
                },
                {
                    "amount": 12566527.0,
                    "amount_type": "AUDA",
                    "date": "2015",
                    "item": "Property rates",
                    "percent": 5.06
                },
                {
                    "amount": 87747924.0,
                    "amount_type": "AUDA",
                    "date": "2015",
                    "item": "Service Charges",
                    "percent": 35.35
                },
                {
                    "amount": 0.0,
                    "amount_type": "AUDA",
                    "date": "2015",
                    "item": "Rental income",
                    "percent": 0
                },
                {
                    "amount": 22814489.0,
                    "amount_type": "AUDA",
                    "date": "2015",
                    "item": "Interest and investments",
                    "percent": 9.19
                },
                {
                    "amount": 535620.0,
                    "amount_type": "AUDA",
                    "date": "2015",
                    "item": "Fines",
                    "percent": 0.22
                },
                {
                    "amount": 877.0,
                    "amount_type": "AUDA",
                    "date": "2015",
                    "item": "Licenses and Permits",
                    "percent": 0.0
                },
                {
                    "amount": 0.0,
                    "amount_type": "AUDA",
                    "date": "2015",
                    "item": "Agency services",
                    "percent": 0
                },
                {
                    "amount": 87209036.0,
                    "amount_type": "AUDA",
                    "date": "2015",
                    "item": "Government Transfers for Operating Expenses",
                    "percent": 35.13
                },
                {
                    "amount": 32347672.0,
                    "amount_type": "AUDA",
                    "date": "2015",
                    "item": "Government Transfers for Capital Expenses",
                    "percent": 13.03
                },
                {
                    "amount": 4998792.0,
                    "amount_type": "AUDA",
                    "date": "2015",
                    "item": "Other",
                    "percent": 2.01
                },
                {
                    "amount": 15649762.0,
                    "amount_type": "ORGB",
                    "date": "2019 budget",
                    "item": "Property rates",
                    "percent": 5.33
                },
                {
                    "amount": 96942477.0,
                    "amount_type": "ORGB",
                    "date": "2019 budget",
                    "item": "Service Charges",
                    "percent": 33.01
                },
                {
                    "amount": 1112000.0,
                    "amount_type": "ORGB",
                    "date": "2019 budget",
                    "item": "Rental income",
                    "percent": 0.38
                },
                {
                    "amount": 28833675.0,
                    "amount_type": "ORGB",
                    "date": "2019 budget",
                    "item": "Interest and investments",
                    "percent": 9.82
                },
                {
                    "amount": 1000000.0,
                    "amount_type": "ORGB",
                    "date": "2019 budget",
                    "item": "Fines",
                    "percent": 0.34
                },
                {
                    "amount": 0.0,
                    "amount_type": "ORGB",
                    "date": "2019 budget",
                    "item": "Licenses and Permits",
                    "percent": 0
                },
                {
                    "amount": 0.0,
                    "amount_type": "ORGB",
                    "date": "2019 budget",
                    "item": "Agency services",
                    "percent": 0
                },
                {
                    "amount": 80793950.0,
                    "amount_type": "ORGB",
                    "date": "2019 budget",
                    "item": "Government Transfers for Operating Expenses",
                    "percent": 27.51
                },
                {
                    "amount": 58621050.0,
                    "amount_type": "ORGB",
                    "date": "2019 budget",
                    "item": "Government Transfers for Capital Expenses",
                    "percent": 19.96
                },
                {
                    "amount": 10691301.0,
                    "amount_type": "ORGB",
                    "date": "2019 budget",
                    "item": "Other",
                    "percent": 3.64
                }
            ]
        },
        "revenue_sources": {
            "government": {
                "amount": 114194192.0,
                "items": [
                    {
                        "amount.sum": 72416619.0,
                        "amount_type.code": "AUDA",
                        "financial_year_end.year": 2018,
                        "item.code": "1600",
                        "item.label": "Transfers Recognised - Operating"
                    },
                    {
                        "amount.sum": 41777573.0,
                        "amount_type.code": "AUDA",
                        "financial_year_end.year": 2018,
                        "item.code": "1610",
                        "item.label": "Transfers Recognised - Capital"
                    }
                ],
                "percent": 40.03
            },
            "local": {
                "amount": 171076845.0,
                "items": [
                    {
                        "amount.sum": 13931288.0,
                        "amount_type.code": "AUDA",
                        "financial_year_end.year": 2018,
                        "item.code": "0200",
                        "item.label": "Property Rates"
                    },
                    {
                        "amount.sum": 0.0,
                        "amount_type.code": "AUDA",
                        "financial_year_end.year": 2018,
                        "item.code": "0300",
                        "item.label": "Property Rates - Penalties And Collection Charges"
                    },
                    {
                        "amount.sum": 117706855.0,
                        "amount_type.code": "AUDA",
                        "financial_year_end.year": 2018,
                        "item.code": "0400",
                        "item.label": "Service Charges"
                    },
                    {
                        "amount.sum": 0.0,
                        "amount_type.code": "AUDA",
                        "financial_year_end.year": 2018,
                        "item.code": "0700",
                        "item.label": "Rent Of Facilities And Equipment"
                    },
                    {
                        "amount.sum": 763992.0,
                        "amount_type.code": "AUDA",
                        "financial_year_end.year": 2018,
                        "item.code": "0800",
                        "item.label": "Interest Earned - External Investments"
                    },
                    {
                        "amount.sum": 27349484.0,
                        "amount_type.code": "AUDA",
                        "financial_year_end.year": 2018,
                        "item.code": "1000",
                        "item.label": "Interest Earned - Outstanding Debtors"
                    },
                    {
                        "amount.sum": 33675.0,
                        "amount_type.code": "AUDA",
                        "financial_year_end.year": 2018,
                        "item.code": "1100",
                        "item.label": "Dividends Received"
                    },
                    {
                        "amount.sum": 527300.0,
                        "amount_type.code": "AUDA",
                        "financial_year_end.year": 2018,
                        "item.code": "1300",
                        "item.label": "Fines"
                    },
                    {
                        "amount.sum": 0.0,
                        "amount_type.code": "AUDA",
                        "financial_year_end.year": 2018,
                        "item.code": "1400",
                        "item.label": "Licenses and Permits"
                    },
                    {
                        "amount.sum": 0.0,
                        "amount_type.code": "AUDA",
                        "financial_year_end.year": 2018,
                        "item.code": "1500",
                        "item.label": "Agency Services"
                    },
                    {
                        "amount.sum": 10764251.0,
                        "amount_type.code": "AUDA",
                        "financial_year_end.year": 2018,
                        "item.code": "1700",
                        "item.label": "Other Revenue"
                    },
                    {
                        "amount.sum": 0.0,
                        "amount_type.code": "AUDA",
                        "financial_year_end.year": 2018,
                        "item.code": "1800",
                        "item.label": "Gain On Disposal Of Property, Plant & Equipment"
                    }
                ],
                "percent": 59.97
            },
            "rating": "ave",
            "ref": {
                "title": "Local Government Equitable Share",
                "url": "http://mfma.treasury.gov.za/Media_Releases/LGESDiscussions/Pages/default.aspx"
            },
            "year": 2018
        },
        "wasteful_exp": {
            "ref": {
                "title": "Circular 71",
                "url": "http://mfma.treasury.gov.za/Circulars/Pages/Circular71.aspx"
            },
            "values": [
                {
                    "date": 2017,
                    "rating": "bad",
                    "result": 40.73
                },
                {
                    "date": 2016,
                    "rating": "bad",
                    "result": 27.69
                },
                {
                    "date": 2015,
                    "rating": "bad",
                    "result": 95.66
                },
                {
                    "date": 2014,
                    "rating": null,
                    "result": null
                }
            ]
        }
    },
    "mayoral_staff": {
        "officials": [
            {
                "email": "mayor@mantsopa.co.za",
                "fax_number": "051 924 2213",
                "name": "M E Tsoene",
                "office_phone": "051 924 0654",
                "role": "Mayor/Executive Mayor",
                "secretary": {
                    "email": "mayor@manatsopa.co.za",
                    "fax_number": "051 924 0020",
                    "name": "M E Tladi",
                    "office_phone": "051 924 0654",
                    "role": "Secretary of Mayor/Executive Mayor",
                    "title": "Ms"
                },
                "title": "Cllr"
            },
            {
                "email": "masejane@mantsopa.co.za",
                "fax_number": "051 924 0020",
                "name": "T P Masejane",
                "office_phone": "051 924 0654",
                "role": "Municipal Manager",
                "secretary": {
                    "email": "mmsecretary@mantsopa.co.za",
                    "fax_number": "051 924 0020",
                    "name": "D J Noe",
                    "office_phone": "051 924 0654",
                    "role": "Secretary of Municipal Manager",
                    "title": "Ms"
                },
                "title": "Mr"
            },
            {
                "email": null,
                "fax_number": null,
                "name": null,
                "office_phone": null,
                "role": "Deputy Mayor/Executive Mayor",
                "title": null
            },
            {
                "email": "makoae@mantsopa.co.za",
                "fax_number": "051 924 0020",
                "name": "A M Makoae",
                "office_phone": "051 924 0654",
                "role": "Chief Financial Officer",
                "secretary": {
                    "email": "cfosecretary@mantsopa.co.za",
                    "fax_number": "051 924 0020",
                    "name": "M L Mahloko",
                    "office_phone": "051 924 0654",
                    "role": "Secretary of Financial Manager",
                    "title": "Ms"
                },
                "title": "Mr"
            }
        ],
        "updated_date": "July 2019"
    },
    "muni_contact": {
        "phone_number": "051 924 0654",
        "street_address_1": "Civic Centre",
        "street_address_2": "Joubert Street",
        "street_address_3": "Ladybrand",
        "street_address_4": "9745",
        "url": "http://www.mantsopa.fs.gov.za"
    }
}